fuzzy_types/__init__.py
fuzzy_types/configuration.py
fuzzy_types/fuzzy.py
fuzzy_types/utils.py
fuzzy_types/etc/fuzzy_types.yml
tests/__init__.py
tests/conftest.py
tests/test_fuzzydict.py
tests/test_fuzzylist.py
tests/test_fuzzystr.py
fuzzy_types-0.1.3.dist-info/LICENSE.md
fuzzy_types-0.1.3.dist-info/METADATA
fuzzy_types-0.1.3.dist-info/WHEEL
fuzzy_types-0.1.3.dist-info/top_level.txt
fuzzy_types-0.1.3.dist-info/RECORD
